{"tag":"section","attrib":{"id":"id0cf5819c-3a70-11f1-a648-bee82ed8a795","identifier":"/us/usc/t20/s1071"},"text":null,"children":[{"tag":"num","attrib":{"value":"1071"},"text":"§ 1071.","children":[],"tail":null},{"tag":"heading","attrib":{},"text":" Statement of purpose; nondiscrimination; and appropriations authorized","children":[],"tail":null},{"tag":"subsection","attrib":{"id":"id0cf5819d-3a70-11f1-a648-bee82ed8a795","identifier":"/us/usc/t20/s1071/a"},"text":null,"children":[{"tag":"num","attrib":{"value":"a"},"text":"(a)","children":[],"tail":null},{"tag":"heading","attrib":{},"text":" Purpose; discrimination prohibited","children":[],"tail":null},{"tag":"paragraph","attrib":{"id":"id0cf5819e-3a70-11f1-a648-bee82ed8a795","identifier":"/us/usc/t20/s1071/a/1"},"text":null,"children":[{"tag":"num","attrib":{"value":"1"},"text":"(1)","children":[],"tail":null},{"tag":"heading","attrib":{},"text":" Purpose","children":[],"tail":null},{"tag":"chapeau","attrib":{},"text":"The purpose of this part is to enable the Secretary—","children":[],"tail":null},{"tag":"subparagraph","attrib":{"id":"id0cf5819f-3a70-11f1-a648-bee82ed8a795","identifier":"/us/usc/t20/s1071/a/1/A"},"text":null,"children":[{"tag":"num","attrib":{"value":"A"},"text":"(A)","children":[],"tail":null},{"tag":"content","attrib":{},"text":" to encourage States and nonprofit private institutions and organizations to establish adequate loan insurance programs for students in eligible institutions (as defined in ","children":[{"tag":"ref","attrib":{"href":"/us/usc/t20/s1085"},"text":"section 1085 of this title","children":[],"tail":"),"}],"tail":"\n"}],"tail":"\n"},{"tag":"subparagraph","attrib":{"id":"id0cf581a0-3a70-11f1-a648-bee82ed8a795","identifier":"/us/usc/t20/s1071/a/1/B"},"text":null,"children":[{"tag":"num","attrib":{"value":"B"},"text":"(B)","children":[],"tail":null},{"tag":"content","attrib":{},"text":" to provide a Federal program of student loan insurance for students or lenders who do not have reasonable access to a State or private nonprofit program of student loan insurance covered by an agreement under ","children":[{"tag":"ref","attrib":{"href":"/us/usc/t20/s1078/b"},"text":"section 1078(b) of this title","children":[],"tail":","}],"tail":"\n"}],"tail":"\n"},{"tag":"subparagraph","attrib":{"id":"id0cf581a1-3a70-11f1-a648-bee82ed8a795","identifier":"/us/usc/t20/s1071/a/1/C"},"text":null,"children":[{"tag":"num","attrib":{"value":"C"},"text":"(C)","children":[],"tail":null},{"tag":"content","attrib":{},"text":" to pay a portion of the interest on loans to qualified students which are insured under this part, and","children":[],"tail":"\n"}],"tail":"\n"},{"tag":"subparagraph","attrib":{"id":"id0cf581a2-3a70-11f1-a648-bee82ed8a795","identifier":"/us/usc/t20/s1071/a/1/D"},"text":null,"children":[{"tag":"num","attrib":{"value":"D"},"text":"(D)","children":[],"tail":null},{"tag":"content","attrib":{},"text":" to guarantee a portion of each loan insured under a program of a State or of a nonprofit private institution or organization which meets the requirements of ","children":[{"tag":"ref","attrib":{"href":"/us/usc/t20/s1078/a/1/B"},"text":"section 1078(a)(1)(B) of this title","children":[],"tail":"."}],"tail":"\n"}],"tail":"\n"}],"tail":"\n"},{"tag":"paragraph","attrib":{"id":"id0cf581a3-3a70-11f1-a648-bee82ed8a795","identifier":"/us/usc/t20/s1071/a/2"},"text":null,"children":[{"tag":"num","attrib":{"value":"2"},"text":"(2)","children":[],"tail":null},{"tag":"heading","attrib":{},"text":" Discrimination by creditors prohibited","children":[],"tail":null},{"tag":"content","attrib":{},"text":null,"children":[{"tag":"p","attrib":{},"text":"No agency, organization, institution, bank, credit union, corporation, or other lender who regularly extends, renews, or continues credit or provides insurance under this part shall exclude from receipt or deny the benefits of, or discriminate against any borrower or applicant in obtaining, such credit or insurance on the basis of race, national origin, religion, sex, marital status, age, or handicapped status.","children":[],"tail":"\n"}],"tail":"\n"}],"tail":"\n"}],"tail":"\n"},{"tag":"subsection","attrib":{"id":"id0cf581a4-3a70-11f1-a648-bee82ed8a795","identifier":"/us/usc/t20/s1071/b"},"text":null,"children":[{"tag":"num","attrib":{"value":"b"},"text":"(b)","children":[],"tail":null},{"tag":"heading","attrib":{},"text":" Authorization of appropriations","children":[],"tail":null},{"tag":"chapeau","attrib":{},"text":"For the purpose of carrying out this part—","children":[],"tail":null},{"tag":"paragraph","attrib":{"id":"id0cf581a5-3a70-11f1-a648-bee82ed8a795","identifier":"/us/usc/t20/s1071/b/1"},"text":null,"children":[{"tag":"num","attrib":{"value":"1"},"text":"(1)","children":[],"tail":null},{"tag":"content","attrib":{},"text":" there are authorized to be appropriated to the student loan insurance fund (established by ","children":[{"tag":"ref","attrib":{"href":"/us/usc/t20/s1081"},"text":"section 1081 of this title","children":[],"tail":") (A) the sum of $1,000,000, and (B) such further sums, if any, as may become necessary for the adequacy of the student loan insurance fund,"}],"tail":"\n"}],"tail":"\n"},{"tag":"paragraph","attrib":{"id":"id0cf581a6-3a70-11f1-a648-bee82ed8a795","identifier":"/us/usc/t20/s1071/b/2"},"text":null,"children":[{"tag":"num","attrib":{"value":"2"},"text":"(2)","children":[],"tail":null},{"tag":"content","attrib":{},"text":" there are authorized to be appropriated, for payments under ","children":[{"tag":"ref","attrib":{"href":"/us/usc/t20/s1078"},"text":"section 1078 of this title","children":[],"tail":" with respect to interest on student loans and for payments under "},{"tag":"ref","attrib":{"href":"/us/usc/t20/s1087"},"text":"section 1087 of this title","children":[],"tail":", such sums for the fiscal year ending "},{"tag":"date","attrib":{"date":"1966-06-30"},"text":"June 30, 1966","children":[],"tail":", and succeeding fiscal years, as may be required therefor,"}],"tail":"\n"}],"tail":"\n"},{"tag":"paragraph","attrib":{"id":"id0cf581a7-3a70-11f1-a648-bee82ed8a795","identifier":"/us/usc/t20/s1071/b/3"},"text":null,"children":[{"tag":"num","attrib":{"value":"3"},"text":"(3)","children":[],"tail":null},{"tag":"content","attrib":{},"text":" there is authorized to be appropriated the sum of $17,500,000 for making advances pursuant to ","children":[{"tag":"ref","attrib":{"href":"/us/usc/t20/s1072"},"text":"section 1072 of this title","children":[],"tail":" for the reserve funds of State and nonprofit private student loan insurance programs,"}],"tail":"\n"}],"tail":"\n"},{"tag":"paragraph","attrib":{"id":"id0cf581a8-3a70-11f1-a648-bee82ed8a795","identifier":"/us/usc/t20/s1071/b/4"},"text":null,"children":[{"tag":"num","attrib":{"value":"4"},"text":"(4)","children":[],"tail":null},{"tag":"content","attrib":{},"text":" there are authorized to be appropriated (A) the sum of $12,500,000 for making advances after ","children":[{"tag":"date","attrib":{"date":"1968-06-30"},"text":"June 30, 1968","children":[],"tail":", pursuant to sections 1072(a) and (b) of this title, and (B) such sums as may be necessary for making advances pursuant to "},{"tag":"ref","attrib":{"href":"/us/usc/t20/s1072/c"},"text":"section 1072(c) of this title","children":[],"tail":", for the reserve funds of State and nonprofit private student loan insurance programs,"}],"tail":"\n"}],"tail":"\n"},{"tag":"paragraph","attrib":{"id":"id0cf581a9-3a70-11f1-a648-bee82ed8a795","identifier":"/us/usc/t20/s1071/b/5"},"text":null,"children":[{"tag":"num","attrib":{"value":"5"},"text":"(5)","children":[],"tail":null},{"tag":"content","attrib":{},"text":" there are authorized to be appropriated such sums as may be necessary for the purpose of paying a loan processing and issuance fee in accordance with ","children":[{"tag":"ref","attrib":{"href":"/us/usc/t20/s1078/f"},"text":"section 1078(f) of this title","children":[],"tail":" to guaranty agencies, and"}],"tail":"\n"}],"tail":"\n"},{"tag":"paragraph","attrib":{"id":"id0cf581aa-3a70-11f1-a648-bee82ed8a795","identifier":"/us/usc/t20/s1071/b/6"},"text":null,"children":[{"tag":"num","attrib":{"value":"6"},"text":"(6)","children":[],"tail":null},{"tag":"content","attrib":{},"text":" there is authorized to be appropriated, and there are appropriated, out of any money in the Treasury not otherwise appropriated, such sums as may be necessary for the purpose of carrying out ","children":[{"tag":"ref","attrib":{"href":"/us/usc/t20/s1072/c/7"},"text":"section 1072(c)(7) of this title","children":[],"tail":"."}],"tail":"\n"}],"tail":"\n\n"},{"tag":"continuation","attrib":{},"text":"Sums appropriated under paragraphs (1), (2), (4), and (5) of this subsection shall remain available until expended, except that no sums may be expended after ","children":[{"tag":"date","attrib":{"date":"2010-06-30"},"text":"June 30, 2010","children":[],"tail":", with respect to loans under this part for which the first disbursement is after such date. No additional sums are authorized to be appropriated under paragraph (3) or (4) of this subsection by reason of the reenactment of such paragraphs by the Higher Education Amendments of 1986."}],"tail":"\n"}],"tail":"\n"},{"tag":"subsection","attrib":{"id":"id0cf581ab-3a70-11f1-a648-bee82ed8a795","identifier":"/us/usc/t20/s1071/c"},"text":null,"children":[{"tag":"num","attrib":{"value":"c"},"text":"(c)","children":[],"tail":null},{"tag":"heading","attrib":{},"text":" Designation","children":[],"tail":null},{"tag":"content","attrib":{},"text":null,"children":[{"tag":"p","attrib":{},"text":"The program established under this part shall be referred to as the “Robert T. Stafford Federal Student Loan Program”. Loans made pursuant to sections 1077 and 1078 of this title shall be known as “Federal Stafford Loans”.","children":[],"tail":"\n"}],"tail":"\n"}],"tail":"\n"},{"tag":"subsection","attrib":{"id":"id0cf581ac-3a70-11f1-a648-bee82ed8a795","identifier":"/us/usc/t20/s1071/d"},"text":null,"children":[{"tag":"num","attrib":{"value":"d"},"text":"(d)","children":[],"tail":null},{"tag":"heading","attrib":{},"text":" Termination of authority to make or insure new loans","children":[],"tail":null},{"tag":"chapeau","attrib":{},"text":"Notwithstanding paragraphs (1) through (6) of subsection (b) or any other provision of law—","children":[],"tail":null},{"tag":"paragraph","attrib":{"id":"id0cf581ad-3a70-11f1-a648-bee82ed8a795","identifier":"/us/usc/t20/s1071/d/1"},"text":null,"children":[{"tag":"num","attrib":{"value":"1"},"text":"(1)","children":[],"tail":null},{"tag":"content","attrib":{},"text":" no new loans (including consolidation loans) may be made or insured under this part after ","children":[{"tag":"date","attrib":{"date":"2010-06-30"},"text":"June 30, 2010","children":[],"tail":"; and"}],"tail":"\n"}],"tail":"\n"},{"tag":"paragraph","attrib":{"id":"id0cf581ae-3a70-11f1-a648-bee82ed8a795","identifier":"/us/usc/t20/s1071/d/2"},"text":null,"children":[{"tag":"num","attrib":{"value":"2"},"text":"(2)","children":[],"tail":null},{"tag":"content","attrib":{},"text":" no funds are authorized to be appropriated, or may be expended, under this chapter or any other Act to make or insure loans under this part (including consolidation loans) for which the first disbursement is after ","children":[{"tag":"date","attrib":{"date":"2010-06-30"},"text":"June 30, 2010","children":[],"tail":","}],"tail":"\n"}],"tail":"\n\n"},{"tag":"continuation","attrib":{},"text":"except as expressly authorized by an Act of Congress enacted after ","children":[{"tag":"date","attrib":{"date":"2010-03-30"},"text":"March 30, 2010","children":[],"tail":"."}],"tail":"\n"}],"tail":"\n"},{"tag":"sourceCredit","attrib":{"id":"id0cf581af-3a70-11f1-a648-bee82ed8a795"},"text":"(","children":[{"tag":"ref","attrib":{"href":"/us/pl/89/329/tIV/s421"},"text":"Pub. L. 89–329, title IV, § 421","children":[],"tail":", as added "},{"tag":"ref","attrib":{"href":"/us/pl/99/498/tIV/s402/a"},"text":"Pub. L. 99–498, title IV, § 402(a)","children":[],"tail":", "},{"tag":"date","attrib":{"date":"1986-10-17"},"text":"Oct. 17, 1986","children":[],"tail":", "},{"tag":"ref","attrib":{"href":"/us/stat/100/1353"},"text":"100 Stat. 1353","children":[],"tail":"; amended "},{"tag":"ref","attrib":{"href":"/us/pl/100/297/tII/s2601/a"},"text":"Pub. L. 100–297, title II, § 2601(a)","children":[],"tail":", "},{"tag":"date","attrib":{"date":"1988-04-28"},"text":"Apr. 28, 1988","children":[],"tail":", "},{"tag":"ref","attrib":{"href":"/us/stat/102/330"},"text":"102 Stat. 330","children":[],"tail":"; "},{"tag":"ref","attrib":{"href":"/us/pl/100/369/s8"},"text":"Pub. L. 100–369, § 8","children":[],"tail":", "},{"tag":"date","attrib":{"date":"1988-07-18"},"text":"July 18, 1988","children":[],"tail":", "},{"tag":"ref","attrib":{"href":"/us/stat/102/837"},"text":"102 Stat. 837","children":[],"tail":"; "},{"tag":"ref","attrib":{"href":"/us/pl/102/325/tIV/s411/a/2"},"text":"Pub. L. 102–325, title IV, § 411(a)(2)","children":[],"tail":", (c), "},{"tag":"date","attrib":{"date":"1992-07-23"},"text":"July 23, 1992","children":[],"tail":", "},{"tag":"ref","attrib":{"href":"/us/stat/106/510"},"text":"106 Stat. 510","children":[],"tail":", 511; "},{"tag":"ref","attrib":{"href":"/us/pl/105/244/tIV/s411"},"text":"Pub. L. 105–244, title IV, § 411","children":[],"tail":", "},{"tag":"date","attrib":{"date":"1998-10-07"},"text":"Oct. 7, 1998","children":[],"tail":", "},{"tag":"ref","attrib":{"href":"/us/stat/112/1673"},"text":"112 Stat. 1673","children":[],"tail":"; "},{"tag":"ref","attrib":{"href":"/us/pl/109/171/tVIII/s8004/a"},"text":"Pub. L. 109–171, title VIII, § 8004(a)","children":[],"tail":", "},{"tag":"date","attrib":{"date":"2006-02-08"},"text":"Feb. 8, 2006","children":[],"tail":", "},{"tag":"ref","attrib":{"href":"/us/stat/120/158"},"text":"120 Stat. 158","children":[],"tail":"; "},{"tag":"ref","attrib":{"href":"/us/pl/110/227/s6/a"},"text":"Pub. L. 110–227, § 6(a)","children":[],"tail":", "},{"tag":"date","attrib":{"date":"2008-05-07"},"text":"May 7, 2008","children":[],"tail":", "},{"tag":"ref","attrib":{"href":"/us/stat/122/746"},"text":"122 Stat. 746","children":[],"tail":"; "},{"tag":"ref","attrib":{"href":"/us/pl/111/152/tII/s2201"},"text":"Pub. L. 111–152, title II, § 2201","children":[],"tail":", "},{"tag":"date","attrib":{"date":"2010-03-30"},"text":"Mar. 30, 2010","children":[],"tail":", "},{"tag":"ref","attrib":{"href":"/us/stat/124/1074"},"text":"124 Stat. 1074","children":[],"tail":".)"}],"tail":"\n"},{"tag":"notes","attrib":{"type":"uscNote","id":"id0cf581b0-3a70-11f1-a648-bee82ed8a795"},"text":"\n","children":[{"tag":"note","attrib":{"role":"crossHeading","topic":"editorialNotes","id":"id0cf581b1-3a70-11f1-a648-bee82ed8a795"},"text":null,"children":[{"tag":"heading","attrib":{},"text":null,"children":[{"tag":"b","attrib":{},"text":"Editorial Notes","children":[],"tail":null}],"tail":null}],"tail":"\n"},{"tag":"note","attrib":{"topic":"referencesInText","id":"id0cf581b2-3a70-11f1-a648-bee82ed8a795"},"text":"\n","children":[{"tag":"heading","attrib":{},"text":"References in Text","children":[],"tail":null},{"tag":"p","attrib":{},"text":"The Higher Education Amendments of 1986, referred to in subsec. (b), is ","children":[{"tag":"ref","attrib":{"href":"/us/pl/99/498"},"text":"Pub. L. 99–498","children":[],"tail":", "},{"tag":"date","attrib":{"date":"1986-10-17"},"text":"Oct. 17, 1986","children":[],"tail":", "},{"tag":"ref","attrib":{"href":"/us/stat/100/1268"},"text":"100 Stat. 1268","children":[],"tail":". For complete classification of this Act to the Code, see Short Title note set out under "},{"tag":"ref","attrib":{"href":"/us/usc/t20/s1001"},"text":"section 1001 of this title","children":[],"tail":" and Tables."}],"tail":"\n"}],"tail":"\n"},{"tag":"note","attrib":{"topic":"codification","id":"id0cf581b3-3a70-11f1-a648-bee82ed8a795"},"text":null,"children":[{"tag":"heading","attrib":{},"text":"Codification","children":[],"tail":"\n"},{"tag":"p","attrib":{},"text":"Another ","children":[{"tag":"ref","attrib":{"href":"/us/pl/105/244/s411"},"text":"section 411 of Pub. L. 105–244","children":[],"tail":" enacted subpart 8 (§ 1070f et seq.) of part A of this subchapter."}],"tail":"\n"}],"tail":"\n"},{"tag":"note","attrib":{"topic":"priorProvisions","id":"id0cf581b4-3a70-11f1-a648-bee82ed8a795"},"text":null,"children":[{"tag":"heading","attrib":{},"text":"Prior Provisions","children":[],"tail":null},{"tag":"p","attrib":{},"text":"A prior section 1071, ","children":[{"tag":"ref","attrib":{"href":"/us/pl/89/329/tIV/s421"},"text":"Pub. L. 89–329, title IV, § 421","children":[],"tail":", "},{"tag":"date","attrib":{"date":"1965-11-08"},"text":"Nov. 8, 1965","children":[],"tail":", "},{"tag":"ref","attrib":{"href":"/us/stat/79/1236"},"text":"79 Stat. 1236","children":[],"tail":"; "},{"tag":"ref","attrib":{"href":"/us/pl/90/460"},"text":"Pub. L. 90–460","children":[],"tail":", §§ 2(b)(3), 3(a), "},{"tag":"date","attrib":{"date":"1968-08-03"},"text":"Aug. 3, 1968","children":[],"tail":", "},{"tag":"ref","attrib":{"href":"/us/stat/82/635"},"text":"82 Stat. 635","children":[],"tail":", 636; "},{"tag":"ref","attrib":{"href":"/us/pl/90/575/tI"},"text":"Pub. L. 90–575, title I","children":[],"tail":", §§ 113(b)(1), 114(a), 119(b), "},{"tag":"date","attrib":{"date":"1968-10-16"},"text":"Oct. 16, 1968","children":[],"tail":", "},{"tag":"ref","attrib":{"href":"/us/stat/82/1021"},"text":"82 Stat. 1021","children":[],"tail":", 1027; "},{"tag":"ref","attrib":{"href":"/us/pl/94/482/tI/s127/a"},"text":"Pub. L. 94–482, title I, § 127(a)","children":[],"tail":", "},{"tag":"date","attrib":{"date":"1976-10-12"},"text":"Oct. 12, 1976","children":[],"tail":", "},{"tag":"ref","attrib":{"href":"/us/stat/90/2099"},"text":"90 Stat. 2099","children":[],"tail":"; "},{"tag":"ref","attrib":{"href":"/us/pl/95/43/s1/a/8"},"text":"Pub. L. 95–43, § 1(a)(8)","children":[],"tail":"–(10), "},{"tag":"date","attrib":{"date":"1977-06-15"},"text":"June 15, 1977","children":[],"tail":", "},{"tag":"ref","attrib":{"href":"/us/stat/91/213"},"text":"91 Stat. 213","children":[],"tail":"; "},{"tag":"ref","attrib":{"href":"/us/pl/96/374/tXIII/s1391/a/1"},"text":"Pub. L. 96–374, title XIII, § 1391(a)(1)","children":[],"tail":", (2), "},{"tag":"date","attrib":{"date":"1980-10-03"},"text":"Oct. 3, 1980","children":[],"tail":", "},{"tag":"ref","attrib":{"href":"/us/stat/94/1503"},"text":"94 Stat. 1503","children":[],"tail":"; "},{"tag":"ref","attrib":{"href":"/us/pl/98/79/s6"},"text":"Pub. L. 98–79, § 6","children":[],"tail":", "},{"tag":"date","attrib":{"date":"1983-08-15"},"text":"Aug. 15, 1983","children":[],"tail":", "},{"tag":"ref","attrib":{"href":"/us/stat/97/482"},"text":"97 Stat. 482","children":[],"tail":", related to statement of purpose of, appropriations for, and implementation of programs to provide low-interest insured loans to students in institutions of higher education, prior to the general revision of this part by "},{"tag":"ref","attrib":{"href":"/us/pl/99/498"},"text":"Pub. L. 99–498","children":[],"tail":"."}],"tail":"\n"}],"tail":"\n"},{"tag":"note","attrib":{"topic":"amendments","id":"id0cf581b5-3a70-11f1-a648-bee82ed8a795"},"text":null,"children":[{"tag":"heading","attrib":{},"text":"Amendments","children":[],"tail":null},{"tag":"p","attrib":{},"text":"2010—Subsec. (b). ","children":[{"tag":"ref","attrib":{"href":"/us/pl/111/152/s2201/1"},"text":"Pub. L. 111–152, § 2201(1)","children":[],"tail":", inserted “, except that no sums may be expended after "},{"tag":"date","attrib":{"date":"2010-06-30"},"text":"June 30, 2010","children":[],"tail":", with respect to loans under this part for which the first disbursement is after such date” after “expended” in concluding provisions."}],"tail":"\n"},{"tag":"p","attrib":{},"text":"Subsec. (d). ","children":[{"tag":"ref","attrib":{"href":"/us/pl/111/152/s2201/2"},"text":"Pub. L. 111–152, § 2201(2)","children":[],"tail":", added subsec. (d)."}],"tail":"\n"},{"tag":"p","attrib":{},"text":"2008—Subsec. (b)(6). ","children":[{"tag":"ref","attrib":{"href":"/us/pl/110/227"},"text":"Pub. L. 110–227","children":[],"tail":" added par. (6)."}],"tail":"\n"},{"tag":"p","attrib":{},"text":"2006—Subsec. (b)(5). ","children":[{"tag":"ref","attrib":{"href":"/us/pl/109/171"},"text":"Pub. L. 109–171","children":[],"tail":" substituted “a loan processing and issuance fee” for “an administrative cost allowance”."}],"tail":"\n"},{"tag":"p","attrib":{},"text":"1998—Subsec. (d). ","children":[{"tag":"ref","attrib":{"href":"/us/pl/105/244"},"text":"Pub. L. 105–244","children":[],"tail":" struck out heading and text of subsec. (d). Text read as follows: “Notwithstanding any other provision of this part, no new loan guarantees shall be issued after "},{"tag":"date","attrib":{"date":"1994-06-30"},"text":"June 30, 1994","children":[],"tail":", if the Secretary does not issue final regulations implementing the changes made to this part under the Higher Education Amendments of 1992 prior to that date. The authority to issue new loan guarantees shall resume upon the Secretary’s issuance of such regulations. This subsection shall not provide the basis for avoiding any requirements for notice and public hearing on such regulations.”"}],"tail":"\n"},{"tag":"p","attrib":{},"text":"1992—Subsec. (c). ","children":[{"tag":"ref","attrib":{"href":"/us/pl/102/325/s411/a/2"},"text":"Pub. L. 102–325, § 411(a)(2)","children":[],"tail":", added subsec. (c) and struck out former subsec. (c) which read as follows: “The program established under this part shall be referred to as the ‘Robert T. Stafford Student Loan Program’. Loans made under this part shall be known as ‘Stafford Loans’.”"}],"tail":"\n"},{"tag":"p","attrib":{},"text":"Subsec. (d). ","children":[{"tag":"ref","attrib":{"href":"/us/pl/102/325/s411/c"},"text":"Pub. L. 102–325, § 411(c)","children":[],"tail":", added subsec. (d)."}],"tail":"\n"},{"tag":"p","attrib":{},"text":"1988—Subsec. (c). ","children":[{"tag":"ref","attrib":{"href":"/us/pl/100/369"},"text":"Pub. L. 100–369","children":[],"tail":" substituted “shall be referred” for “may be referred” and inserted provision identifying loans made under this part as “Stafford Loans”."}],"tail":"\n"},{"tag":"p","attrib":{},"text":null,"children":[{"tag":"ref","attrib":{"href":"/us/pl/100/297"},"text":"Pub. L. 100–297","children":[],"tail":" added subsec. (c)."}],"tail":"\n"}],"tail":"\n"},{"tag":"note","attrib":{"role":"crossHeading","topic":"statutoryNotes","id":"id0cf581b6-3a70-11f1-a648-bee82ed8a795"},"text":null,"children":[{"tag":"heading","attrib":{},"text":null,"children":[{"tag":"b","attrib":{},"text":"Statutory Notes and Related Subsidiaries","children":[],"tail":null}],"tail":null}],"tail":"\n"},{"tag":"note","attrib":{"topic":"effectiveDateOfAmendment","id":"id0cf581b7-3a70-11f1-a648-bee82ed8a795"},"text":null,"children":[{"tag":"heading","attrib":{},"text":"Effective Date of 2008 Amendment","children":[],"tail":null},{"tag":"p","attrib":{},"text":null,"children":[{"tag":"ref","attrib":{"href":"/us/pl/110/227/s6/b"},"text":"Pub. L. 110–227, § 6(b)","children":[],"tail":", "},{"tag":"date","attrib":{"date":"2008-05-07"},"text":"May 7, 2008","children":[],"tail":", "},{"tag":"ref","attrib":{"href":"/us/stat/122/746"},"text":"122 Stat. 746","children":[],"tail":", provided that: "},{"tag":"quotedContent","attrib":{"origin":"/us/pl/110/227/s6/b"},"text":"“The amendments made by subsection (a) [amending this section] shall take effect on the date of enactment of this Act [","children":[{"tag":"date","attrib":{"date":"2008-05-07"},"text":"May 7, 2008","children":[],"tail":"].”"}],"tail":"\n"}],"tail":"\n"}],"tail":"\n"},{"tag":"note","attrib":{"topic":"effectiveDateOfAmendment","id":"id0cf581b8-3a70-11f1-a648-bee82ed8a795"},"text":null,"children":[{"tag":"heading","attrib":{},"text":"Effective Date of 2006 Amendment","children":[],"tail":null},{"tag":"p","attrib":{},"text":"Amendment by ","children":[{"tag":"ref","attrib":{"href":"/us/pl/109/171"},"text":"Pub. L. 109–171","children":[],"tail":" effective "},{"tag":"date","attrib":{"date":"2006-07-01"},"text":"July 1, 2006","children":[],"tail":", except as otherwise provided, see "},{"tag":"ref","attrib":{"href":"/us/pl/109/171/s8001/c"},"text":"section 8001(c) of Pub. L. 109–171","children":[],"tail":", set out as a note under "},{"tag":"ref","attrib":{"href":"/us/usc/t20/s1002"},"text":"section 1002 of this title","children":[],"tail":"."}],"tail":"\n"}],"tail":"\n"},{"tag":"note","attrib":{"topic":"effectiveDateOfAmendment","id":"id0cf581b9-3a70-11f1-a648-bee82ed8a795"},"text":null,"children":[{"tag":"heading","attrib":{},"text":"Effective Date of 1992 Amendment","children":[],"tail":null},{"tag":"p","attrib":{},"text":"Amendment by ","children":[{"tag":"ref","attrib":{"href":"/us/pl/102/325"},"text":"Pub. L. 102–325","children":[],"tail":" effective "},{"tag":"date","attrib":{"date":"1992-07-23"},"text":"July 23, 1992","children":[],"tail":", with changes in the designation or names of loans or programs under this part effective with respect to applications or other documents (used in making such loans) that are printed after "},{"tag":"date","attrib":{"date":"1992-07-23"},"text":"July 23, 1992","children":[],"tail":", see "},{"tag":"ref","attrib":{"href":"/us/pl/102/325/s432"},"text":"section 432 of Pub. L. 102–325","children":[],"tail":", set out as a note under "},{"tag":"ref","attrib":{"href":"/us/usc/t20/s1078"},"text":"section 1078 of this title","children":[],"tail":"."}],"tail":"\n"}],"tail":"\n"},{"tag":"note","attrib":{"topic":"effectiveDateOfAmendment","id":"id0cf581ba-3a70-11f1-a648-bee82ed8a795"},"text":null,"children":[{"tag":"heading","attrib":{},"text":"Effective Date of 1988 Amendment","children":[],"tail":null},{"tag":"p","attrib":{},"text":null,"children":[{"tag":"ref","attrib":{"href":"/us/pl/100/297/tVI/s6303"},"text":"Pub. L. 100–297, title VI, § 6303","children":[],"tail":", "},{"tag":"date","attrib":{"date":"1988-04-28"},"text":"Apr. 28, 1988","children":[],"tail":", "},{"tag":"ref","attrib":{"href":"/us/stat/102/431"},"text":"102 Stat. 431","children":[],"tail":", as amended by "},{"tag":"ref","attrib":{"href":"/us/pl/100/351"},"text":"Pub. L. 100–351","children":[],"tail":", "},{"tag":"date","attrib":{"date":"1988-06-27"},"text":"June 27, 1988","children":[],"tail":", "},{"tag":"ref","attrib":{"href":"/us/stat/102/661"},"text":"102 Stat. 661","children":[],"tail":"; "},{"tag":"ref","attrib":{"href":"/us/pl/106/400/s2"},"text":"Pub. L. 106–400, § 2","children":[],"tail":", "},{"tag":"date","attrib":{"date":"2000-10-30"},"text":"Oct. 30, 2000","children":[],"tail":", "},{"tag":"ref","attrib":{"href":"/us/stat/114/1675"},"text":"114 Stat. 1675","children":[],"tail":", provided that:"},{"tag":"quotedContent","attrib":{"origin":"/us/pl/106/400/s2"},"text":"\n","children":[{"tag":"subsection","attrib":{},"text":null,"children":[{"tag":"num","attrib":{"value":"a"},"text":"“(a)","children":[],"tail":null},{"tag":"heading","attrib":{},"text":" ","children":[{"tag":"inline","attrib":{},"text":"General Rule","children":[],"tail":".—"}],"tail":null},{"tag":"content","attrib":{},"text":"Except as otherwise provided, this Act and the amendments made by this Act [see Tables for classification] shall take effect ","children":[{"tag":"date","attrib":{"date":"1988-07-01"},"text":"July 1, 1988","children":[],"tail":"."}],"tail":"\n"}],"tail":"\n"},{"tag":"subsection","attrib":{},"text":null,"children":[{"tag":"num","attrib":{"value":"b"},"text":"“(b)","children":[],"tail":null},{"tag":"heading","attrib":{},"text":" ","children":[{"tag":"inline","attrib":{},"text":"Special Rules","children":[],"tail":".—"}],"tail":null},{"tag":"paragraph","attrib":{},"text":null,"children":[{"tag":"num","attrib":{"value":"1"},"text":"(1)","children":[],"tail":null},{"tag":"content","attrib":{},"text":" Any provision of this Act or any amendment made by this Act which authorizes appropriations for fiscal year 1988 shall take effect on the date of the enactment of this Act [","children":[{"tag":"date","attrib":{"date":"1988-04-28"},"text":"Apr. 28, 1988","children":[],"tail":"]."}],"tail":"\n"}],"tail":"\n"},{"tag":"paragraph","attrib":{},"text":null,"children":[{"tag":"num","attrib":{"value":"2"},"text":"“(2)","children":[],"tail":null},{"tag":"content","attrib":{},"text":" The provisions of section 2402, relating to the National Center for Vocational Research, shall take effect on ","children":[{"tag":"date","attrib":{"date":"1988-04-10"},"text":"April 10, 1988","children":[],"tail":"."}],"tail":"\n"}],"tail":"\n"},{"tag":"paragraph","attrib":{},"text":null,"children":[{"tag":"num","attrib":{"value":"3"},"text":"“(3)","children":[],"tail":null},{"tag":"content","attrib":{},"text":" The amendments made by section 3403 [amending sections 1221e and 1221e–1 of this title] shall take effect for assessments made after ","children":[{"tag":"date","attrib":{"date":"1989-09-30"},"text":"September 30, 1989","children":[],"tail":", with respect to State data."}],"tail":"\n"}],"tail":"\n"},{"tag":"paragraph","attrib":{},"text":null,"children":[{"tag":"num","attrib":{"value":"4"},"text":"“(4)","children":[],"tail":null},{"tag":"content","attrib":{},"text":" Allotments to States made under chapters 1 and 2 of title I of the Elementary and Secondary Education Act of 1965 [formerly ","children":[{"tag":"ref","attrib":{"href":"/us/usc/t20/s2701"},"text":"20 U.S.C. 2701","children":[],"tail":" et seq., 2911 et seq.] and under the Adult Education Act [formerly "},{"tag":"ref","attrib":{"href":"/us/usc/t20/s1201"},"text":"20 U.S.C. 1201","children":[],"tail":" et seq.] from amounts appropriated by the joint resolution entitled ‘Joint resolution making further continuing appropriations for the fiscal year 1988, and for other purposes’, approved "},{"tag":"date","attrib":{"date":"1987-12-22"},"text":"December 22, 1987","children":[],"tail":" ("},{"tag":"ref","attrib":{"href":"/us/pl/100/202"},"text":"Public Law 100–202","children":[],"tail":"), shall be computed in accordance with the provisions of law applicable to allotments to States under chapters 1 and 2 of the Education Consolidation and Improvement Act of 1981 [formerly "},{"tag":"ref","attrib":{"href":"/us/usc/t20/s3801"},"text":"20 U.S.C. 3801","children":[],"tail":" et seq., 3811 et seq.] and under the Adult Education Act, respectively, as such Acts were in effect on the day before the date of the enactment of this Act ["},{"tag":"date","attrib":{"date":"1988-04-28"},"text":"Apr. 28, 1988","children":[],"tail":"]."}],"tail":"\n"}],"tail":"\n"},{"tag":"paragraph","attrib":{},"text":null,"children":[{"tag":"num","attrib":{"value":"5"},"text":"“(5)","children":[],"tail":null},{"tag":"chapeau","attrib":{},"text":" Amounts appropriated by the joint resolution entitled ‘Joint resolution making further continuing appropriations for the fiscal year 1988, and for other purposes’, approved ","children":[{"tag":"date","attrib":{"date":"1987-12-22"},"text":"December 22, 1987","children":[],"tail":" ("},{"tag":"ref","attrib":{"href":"/us/pl/100/202"},"text":"Public Law 100–202","children":[],"tail":"), for the following programs shall be awarded in accordance with the applicable provisions of law in effect on the day before the date of the enactment of this Act ["},{"tag":"date","attrib":{"date":"1988-04-28"},"text":"Apr. 28, 1988","children":[],"tail":"]:"}],"tail":null},{"tag":"subparagraph","attrib":{},"text":null,"children":[{"tag":"num","attrib":{"value":"A"},"text":"“(A)","children":[],"tail":null},{"tag":"content","attrib":{},"text":" Programs under subchapter D of chapter 2 of the Education Consolidation and Improvement Act of 1981 [formerly ","children":[{"tag":"ref","attrib":{"href":"/us/usc/t20/s3851"},"text":"20 U.S.C. 3851","children":[],"tail":" et seq.], except that projects under section 583(c) [formerly "},{"tag":"ref","attrib":{"href":"/us/usc/t20/s3851/c"},"text":"20 U.S.C. 3851(c)","children":[],"tail":"] may not be reviewed by a program significance panel."}],"tail":"\n"}],"tail":"\n"},{"tag":"subparagraph","attrib":{},"text":null,"children":[{"tag":"num","attrib":{"value":"B"},"text":"“(B)","children":[],"tail":null},{"tag":"content","attrib":{},"text":" National programs under the Adult Education Act [formerly ","children":[{"tag":"ref","attrib":{"href":"/us/usc/t20/s1201"},"text":"20 U.S.C. 1201","children":[],"tail":" et seq.]."}],"tail":"\n"}],"tail":"\n"},{"tag":"subparagraph","attrib":{},"text":null,"children":[{"tag":"num","attrib":{"value":"C"},"text":"“(C)","children":[],"tail":null},{"tag":"content","attrib":{},"text":" Programs under the Indian Education Act [","children":[{"tag":"ref","attrib":{"href":"/us/pl/92/318/tIV"},"text":"Pub. L. 92–318, title IV","children":[],"tail":", see Tables for classification]."}],"tail":"\n"}],"tail":"\n"},{"tag":"subparagraph","attrib":{},"text":null,"children":[{"tag":"num","attrib":{"value":"D"},"text":"“(D)","children":[],"tail":null},{"tag":"content","attrib":{},"text":" Programs under title II of the Education for Economic Security Act [formerly ","children":[{"tag":"ref","attrib":{"href":"/us/usc/t20/s3961"},"text":"20 U.S.C. 3961","children":[],"tail":" et seq.]."}],"tail":"\n"}],"tail":"\n"},{"tag":"subparagraph","attrib":{},"text":null,"children":[{"tag":"num","attrib":{"value":"E"},"text":"“(E)","children":[],"tail":null},{"tag":"content","attrib":{},"text":" The program under section 702 of the McKinney-Vento Homeless Assistance Act [formerly ","children":[{"tag":"ref","attrib":{"href":"/us/usc/t42/s11421"},"text":"42 U.S.C. 11421","children":[],"tail":"]."}],"tail":"\n"}],"tail":"\n"}],"tail":"\n"},{"tag":"paragraph","attrib":{},"text":null,"children":[{"tag":"num","attrib":{"value":"6"},"text":"“(6)","children":[],"tail":null},{"tag":"content","attrib":{},"text":" The provisions of part A of title II of this Act [§§ 2001 to 2034 of ","children":[{"tag":"ref","attrib":{"href":"/us/pl/100/297"},"text":"Pub. L. 100–297","children":[],"tail":", amending sections 236 et seq. and 631 et seq. of this title], excluding sections 2014(e) and 2018 [amending "},{"tag":"ref","attrib":{"href":"/us/usc/t20/s238"},"text":"section 238 of this title","children":[],"tail":" and enacting provisions set out as a note under "},{"tag":"ref","attrib":{"href":"/us/usc/t20/s238"},"text":"section 238 of this title","children":[],"tail":"], shall apply only with respect to amounts appropriated for fiscal years beginning after "},{"tag":"date","attrib":{"date":"1988-09-30"},"text":"September 30, 1988","children":[],"tail":"."}],"tail":"\n"}],"tail":"\n"},{"tag":"paragraph","attrib":{},"text":null,"children":[{"tag":"num","attrib":{"value":"7"},"text":"“(7)","children":[],"tail":null},{"tag":"content","attrib":{},"text":" The amendments made by section 6001 [amending ","children":[{"tag":"ref","attrib":{"href":"/us/usc/t42/s11421"},"text":"section 11421 of Title 42","children":[],"tail":", The Public Health and Welfare], relating to literacy training of homeless adults, shall take effect on "},{"tag":"date","attrib":{"date":"1988-10-01"},"text":"October 1, 1988","children":[],"tail":"."}],"tail":"\n"}],"tail":"\n"},{"tag":"paragraph","attrib":{},"text":null,"children":[{"tag":"num","attrib":{"value":"8"},"text":"“(8)","children":[],"tail":null},{"tag":"content","attrib":{},"text":" Any election under section 5209(b)(1) [","children":[{"tag":"ref","attrib":{"href":"/us/usc/t25/s2508/b/1"},"text":"25 U.S.C. 2508(b)(1)","children":[],"tail":"] conveyed to the Secretary prior to "},{"tag":"date","attrib":{"date":"1988-08-01"},"text":"August 1, 1988","children":[],"tail":", shall take effect for the fiscal year beginning on "},{"tag":"date","attrib":{"date":"1988-10-01"},"text":"October 1, 1988","children":[],"tail":", and thereafter.”"}],"tail":"\n"}],"tail":"\n"}],"tail":"\n"}],"tail":"\n"}],"tail":"\n"}],"tail":"\n"},{"tag":"note","attrib":{"topic":"effectiveDate","id":"id0cf581bb-3a70-11f1-a648-bee82ed8a795"},"text":null,"children":[{"tag":"heading","attrib":{},"text":"Effective Date","children":[],"tail":null},{"tag":"p","attrib":{},"text":null,"children":[{"tag":"ref","attrib":{"href":"/us/pl/99/498/tIV/s402/b"},"text":"Pub. L. 99–498, title IV, § 402(b)","children":[],"tail":"–(d), "},{"tag":"date","attrib":{"date":"1986-10-17"},"text":"Oct. 17, 1986","children":[],"tail":", "},{"tag":"ref","attrib":{"href":"/us/stat/100/1428"},"text":"100 Stat. 1428","children":[],"tail":", 1429, as amended by "},{"tag":"ref","attrib":{"href":"/us/pl/100/50/s22/b"},"text":"Pub. L. 100–50, § 22(b)","children":[],"tail":", "},{"tag":"date","attrib":{"date":"1987-06-03"},"text":"June 3, 1987","children":[],"tail":", "},{"tag":"ref","attrib":{"href":"/us/stat/101/361"},"text":"101 Stat. 361","children":[],"tail":", provided that:"},{"tag":"quotedContent","attrib":{"origin":"/us/pl/100/50/s22/b"},"text":"\n","children":[{"tag":"subsection","attrib":{},"text":null,"children":[{"tag":"num","attrib":{"value":"b"},"text":"“(b)","children":[],"tail":null},{"tag":"heading","attrib":{},"text":" ","children":[{"tag":"inline","attrib":{},"text":"Effective Dates","children":[],"tail":".—"}],"tail":null},{"tag":"chapeau","attrib":{},"text":"The changes made in part B of title IV of the Act [","children":[{"tag":"ref","attrib":{"href":"/us/usc/t20/s1071"},"text":"20 U.S.C. 1071","children":[],"tail":" et seq.] by the amendment made by subsection (a) of this section shall take effect on the date of enactment of this Act ["},{"tag":"date","attrib":{"date":"1986-10-17"},"text":"Oct. 17, 1986","children":[],"tail":"], except—"}],"tail":null},{"tag":"paragraph","attrib":{},"text":null,"children":[{"tag":"num","attrib":{"value":"1"},"text":"“(1)","children":[],"tail":null},{"tag":"content","attrib":{},"text":" as otherwise provided in such part B;","children":[],"tail":"\n"}],"tail":"\n"},{"tag":"paragraph","attrib":{},"text":null,"children":[{"tag":"num","attrib":{"value":"2"},"text":"“(2)","children":[],"tail":null},{"tag":"content","attrib":{},"text":" the changes in sections 427(a)(2)(C) and 428(b)(1)(M) of the Act [","children":[{"tag":"ref","attrib":{"href":"/us/usc/t20/s1077/a/2/C"},"text":"20 U.S.C. 1077(a)(2)(C)","children":[],"tail":", 1078(b)(1)(M)] (other than clauses (viii), (ix), and (x) of each such section) shall apply only to loans to new borrowers that (A) are made to cover the cost of instruction for periods of enrollment beginning on or after "},{"tag":"date","attrib":{"date":"1987-07-01"},"text":"July 1, 1987","children":[],"tail":"; or (B) are disbursed on or after "},{"tag":"date","attrib":{"date":"1987-07-01"},"text":"July 1, 1987","children":[],"tail":";"}],"tail":"\n"}],"tail":"\n"},{"tag":"paragraph","attrib":{},"text":null,"children":[{"tag":"num","attrib":{"value":"3"},"text":"“(3)","children":[],"tail":null},{"tag":"content","attrib":{},"text":" the changes made in sections 425(a), 428(b)(1)(A), and 428(b)(1)(B) of the Act [","children":[{"tag":"ref","attrib":{"href":"/us/usc/t20/s1075/a"},"text":"20 U.S.C. 1075(a)","children":[],"tail":", 1078(b)(1)(A), (B)] shall apply with respect only to loans disbursed on or after "},{"tag":"date","attrib":{"date":"1987-01-01"},"text":"January 1, 1987","children":[],"tail":", or made to cover the costs of instruction for periods of enrollment beginning on or after "},{"tag":"date","attrib":{"date":"1987-01-01"},"text":"January 1, 1987","children":[],"tail":";"}],"tail":"\n"}],"tail":"\n"},{"tag":"paragraph","attrib":{},"text":null,"children":[{"tag":"num","attrib":{"value":"4"},"text":"“(4)","children":[],"tail":null},{"tag":"content","attrib":{},"text":" the changes made in subsections (a), (b), and (d) of section 433 of the Act [","children":[{"tag":"ref","attrib":{"href":"/us/usc/t20/s1083/a"},"text":"20 U.S.C. 1083(a)","children":[],"tail":", (b), (d)] shall apply with respect only to loans disbursed on or after "},{"tag":"date","attrib":{"date":"1987-01-01"},"text":"January 1, 1987","children":[],"tail":", or made to cover the costs of instruction for periods of enrollment beginning on or after "},{"tag":"date","attrib":{"date":"1987-01-01"},"text":"January 1, 1987","children":[],"tail":";"}],"tail":"\n"}],"tail":"\n"},{"tag":"paragraph","attrib":{},"text":null,"children":[{"tag":"num","attrib":{"value":"5"},"text":"“(5)","children":[],"tail":null},{"tag":"content","attrib":{},"text":" the changes in section 428(b)(1)(H) [","children":[{"tag":"ref","attrib":{"href":"/us/usc/t20/s1078/b/1/H"},"text":"20 U.S.C. 1078(b)(1)(H)","children":[],"tail":"] shall apply with respect only to loans for which the borrower files an application on or after "},{"tag":"date","attrib":{"date":"1987-07-01"},"text":"July 1, 1987","children":[],"tail":";"}],"tail":"\n"}],"tail":"\n"},{"tag":"paragraph","attrib":{},"text":null,"children":[{"tag":"num","attrib":{"value":"6"},"text":"“(6)","children":[],"tail":null},{"tag":"content","attrib":{},"text":" the changes in sections 435(d)(5) and 438(d) of the Act [","children":[{"tag":"ref","attrib":{"href":"/us/usc/t20/s1085/d/5"},"text":"20 U.S.C. 1085(d)(5)","children":[],"tail":", 1087–1(d)] shall take effect 30 days after the date of enactment of this Act ["},{"tag":"date","attrib":{"date":"1986-10-17"},"text":"Oct. 17, 1986","children":[],"tail":"]; and"}],"tail":"\n"}],"tail":"\n"},{"tag":"paragraph","attrib":{},"text":null,"children":[{"tag":"num","attrib":{"value":"7"},"text":"“(7)","children":[],"tail":null},{"tag":"content","attrib":{},"text":" the changes made in section 438(b) [","children":[{"tag":"ref","attrib":{"href":"/us/usc/t20/s1087–1/b"},"text":"20 U.S.C. 1087–1(b)","children":[],"tail":"] shall take effect with respect to loans disbursed on or after 30 days after the date of enactment of this Act ["},{"tag":"date","attrib":{"date":"1986-10-17"},"text":"Oct. 17, 1986","children":[],"tail":"] or made to cover the costs of instruction for periods of enrollment beginning on or after 30 days after the date of enactment of this Act."}],"tail":"\n"}],"tail":"\n"}],"tail":"\n"},{"tag":"subsection","attrib":{},"text":null,"children":[{"tag":"num","attrib":{"value":"c"},"text":"“(c)","children":[],"tail":null},{"tag":"heading","attrib":{},"text":" ","children":[{"tag":"inline","attrib":{},"text":"Changes Effective Without Regard to Regulations; Republication of Regulations","children":[],"tail":".—"}],"tail":null},{"tag":"content","attrib":{},"text":"The changes made in part B of title IV of the Act [","children":[{"tag":"ref","attrib":{"href":"/us/usc/t20/s1071"},"text":"20 U.S.C. 1071","children":[],"tail":" et seq.] by the amendment made by subsection (a) of this section shall be effective in accordance with subsection (b) of this section without regard to whether such changes are reflected in the regulations prescribed by the Secretary of Education for the purpose of such part."}],"tail":"\n"}],"tail":"\n"},{"tag":"subsection","attrib":{},"text":null,"children":[{"tag":"num","attrib":{"value":"d"},"text":"“(d)","children":[],"tail":null},{"tag":"heading","attrib":{},"text":" ","children":[{"tag":"inline","attrib":{},"text":"New Borrowers","children":[],"tail":".—"}],"tail":null},{"tag":"content","attrib":{},"text":"For the purpose of this section, the term ‘new borrower’ means, with respect to any date, an individual who on that date has no outstanding balance of principal or interest owing on any loan made, insured, or guaranteed under part B of title IV of the Act [","children":[{"tag":"ref","attrib":{"href":"/us/usc/t20/s1071"},"text":"20 U.S.C. 1071","children":[],"tail":" et seq.].”"}],"tail":"\n"}],"tail":"\n"}],"tail":"\n"}],"tail":"\n"}],"tail":"\n"},{"tag":"note","attrib":{"topic":"miscellaneous","id":"id0cf7f1bc-3a70-11f1-a648-bee82ed8a795"},"text":null,"children":[{"tag":"heading","attrib":{},"text":"Study of Role of Guaranty Agencies","children":[],"tail":null},{"tag":"p","attrib":{},"text":null,"children":[{"tag":"ref","attrib":{"href":"/us/pl/102/325/tXIV/s1401"},"text":"Pub. L. 102–325, title XIV, § 1401","children":[],"tail":", "},{"tag":"date","attrib":{"date":"1992-07-23"},"text":"July 23, 1992","children":[],"tail":", "},{"tag":"ref","attrib":{"href":"/us/stat/106/816"},"text":"106 Stat. 816","children":[],"tail":", directed Secretary of Education to review role of guaranty agencies within Federal Family Education Loan Program by examining administrative and financial operations of such agencies and the relationships between guaranty agencies and State governments and report to Congress within 1 year of "},{"tag":"date","attrib":{"date":"1992-07-23"},"text":"July 23, 1992","children":[],"tail":", on the review, prior to repeal by "},{"tag":"ref","attrib":{"href":"/us/pl/105/332/s6/b/2"},"text":"Pub. L. 105–332, § 6(b)(2)","children":[],"tail":", "},{"tag":"date","attrib":{"date":"1998-10-31"},"text":"Oct. 31, 1998","children":[],"tail":", "},{"tag":"ref","attrib":{"href":"/us/stat/112/3128"},"text":"112 Stat. 3128","children":[],"tail":"."}],"tail":"\n"}],"tail":"\n"},{"tag":"note","attrib":{"topic":"miscellaneous","id":"id0cf7f1bd-3a70-11f1-a648-bee82ed8a795"},"text":null,"children":[{"tag":"heading","attrib":{},"text":"General Accounting Office Reports","children":[],"tail":null},{"tag":"p","attrib":{},"text":null,"children":[{"tag":"ref","attrib":{"href":"/us/pl/99/498/tXIII"},"text":"Pub. L. 99–498, title XIII","children":[],"tail":", §§ 1311–1314, "},{"tag":"date","attrib":{"date":"1986-10-17"},"text":"Oct. 17, 1986","children":[],"tail":", "},{"tag":"ref","attrib":{"href":"/us/stat/100/1583"},"text":"100 Stat. 1583","children":[],"tail":", 1584, as amended by "},{"tag":"ref","attrib":{"href":"/us/pl/100/50/s23/6"},"text":"Pub. L. 100–50, § 23(6)","children":[],"tail":", "},{"tag":"date","attrib":{"date":"1987-06-03"},"text":"June 3, 1987","children":[],"tail":", "},{"tag":"ref","attrib":{"href":"/us/stat/101/362"},"text":"101 Stat. 362","children":[],"tail":", directed Comptroller General to conduct studies on practices of State guaranty agencies and multistate guarantors under the student loan program, on the feasibility and efficiency of permitting students to establish multiple year lines of credit with eligible lenders, on the impact of the multiple disbursement system on the ability of students and institutions of higher education to meet expenses, and on the cost, efficiency, and impact of the consolidation loan program established by "},{"tag":"ref","attrib":{"href":"/us/pl/99/498"},"text":"Pub. L. 99–498","children":[],"tail":", and directed Comptroller General to make and submit a report to Congress on each study not later than two years after "},{"tag":"date","attrib":{"date":"1986-10-17"},"text":"Oct. 17, 1986","children":[],"tail":", prior to repeal by "},{"tag":"ref","attrib":{"href":"/us/pl/105/332/s6/a"},"text":"Pub. L. 105–332, § 6(a)","children":[],"tail":", "},{"tag":"date","attrib":{"date":"1998-10-31"},"text":"Oct. 31, 1998","children":[],"tail":", "},{"tag":"ref","attrib":{"href":"/us/stat/112/3127"},"text":"112 Stat. 3127","children":[],"tail":"."}],"tail":"\n"}],"tail":"\n"}],"tail":"\n"}],"tail":null}
