{"tag":"section","attrib":{"id":"id62917bb2-4962-11f1-add1-b56d3fa293fa","identifier":"/us/usc/t25/s2107"},"text":null,"children":[{"tag":"num","attrib":{"value":"2107"},"text":"§ 2107.","children":[],"tail":null},{"tag":"heading","attrib":{},"text":" Regulations; consultation with Indian organizations; pending agreements","children":[],"tail":null},{"tag":"content","attrib":{},"text":"\n","children":[{"tag":"p","attrib":{},"text":"Within one hundred and eighty days of ","children":[{"tag":"date","attrib":{"date":"1982-12-22"},"text":"December 22, 1982","children":[],"tail":", the Secretary of the Interior shall promulgate rules and regulations to facilitate implementation of this chapter. The Secretary shall, to the extent practicable, consult with national and regional Indian organizations and tribes with expertise in mineral development both in the initial formulation of rules and regulations and any future revision or amendment of such rules and regulations. Where there is pending before the Secretary for his approval a Minerals Agreement of the type authorized by "},{"tag":"ref","attrib":{"href":"/us/usc/t25/s2102"},"text":"section 2102 of this title","children":[],"tail":" which was submitted prior to "},{"tag":"date","attrib":{"date":"1982-12-22"},"text":"December 22, 1982","children":[],"tail":", the Secretary shall evaluate and approve or disapprove such agreement based upon "},{"tag":"ref","attrib":{"href":"/us/usc/t25/s2103"},"text":"section 2103 of this title","children":[],"tail":", but shall not withhold or delay such approval or disapproval on the grounds that the rules and regulations implementing this chapter have not been promulgated."}],"tail":"\n"}],"tail":null},{"tag":"sourceCredit","attrib":{"id":"id62917bb3-4962-11f1-add1-b56d3fa293fa"},"text":"(","children":[{"tag":"ref","attrib":{"href":"/us/pl/97/382/s8"},"text":"Pub. L. 97–382, § 8","children":[],"tail":", "},{"tag":"date","attrib":{"date":"1982-12-22"},"text":"Dec. 22, 1982","children":[],"tail":", "},{"tag":"ref","attrib":{"href":"/us/stat/96/1940"},"text":"96 Stat. 1940","children":[],"tail":".)"}],"tail":"\n"}],"tail":null}
