{"tag":"section","attrib":{"id":"idca8c8270-3a70-11f1-bde1-a5140e158598","identifier":"/us/usc/t43/s2243"},"text":null,"children":[{"tag":"num","attrib":{"value":"2243"},"text":"§ 2243.","children":[],"tail":null},{"tag":"heading","attrib":{},"text":" Temperature control at Shasta Dam, Central Valley Project","children":[],"tail":null},{"tag":"content","attrib":{},"text":"\n","children":[{"tag":"p","attrib":{},"text":"The Secretary is authorized to complete the design and specifications for construction of a device to control the temperature of water releases from Shasta Dam, Central Valley Project, California, and to construct facilities needed to attach such device to the dam. There is authorized to be appropriated to carry out the authority of this section not more than $12,000,000.","children":[],"tail":"\n"}],"tail":null},{"tag":"sourceCredit","attrib":{"id":"idca8c8271-3a70-11f1-bde1-a5140e158598"},"text":"(","children":[{"tag":"ref","attrib":{"href":"/us/pl/102/250/tIII/s303"},"text":"Pub. L. 102–250, title III, § 303","children":[],"tail":", "},{"tag":"date","attrib":{"date":"1992-03-05"},"text":"Mar. 5, 1992","children":[],"tail":", "},{"tag":"ref","attrib":{"href":"/us/stat/106/58"},"text":"106 Stat. 58","children":[],"tail":".)"}],"tail":"\n"}],"tail":null}
