{"tag":"section","attrib":{"id":"id78bd27f7-6992-11f1-ab3f-8b4c043f8cd5","identifier":"/us/usc/t16/s831z"},"text":null,"children":[{"tag":"num","attrib":{"value":"831z"},"text":"§ 831z.","children":[],"tail":null},{"tag":"heading","attrib":{},"text":" Authorization of appropriations","children":[],"tail":null},{"tag":"content","attrib":{},"text":"\n","children":[{"tag":"p","attrib":{},"text":"All appropriations necessary to carry out the provisions of this chapter are authorized.","children":[],"tail":"\n"}],"tail":null},{"tag":"sourceCredit","attrib":{"id":"id78bd27f8-6992-11f1-ab3f-8b4c043f8cd5"},"text":"(","children":[{"tag":"ref","attrib":{"href":"/us/act/1933-05-18/ch32/s27"},"text":"May 18, 1933, ch. 32, § 27","children":[],"tail":", "},{"tag":"ref","attrib":{"href":"/us/stat/48/71"},"text":"48 Stat. 71","children":[],"tail":".)"}],"tail":"\n"}],"tail":null}
